json_schema/__init__.py
json_schema/fields.py
json_schema/forms.py
json_schema/models.py
json_schema/widgets.py
json_schema/templates/json-schema-widget.html
django_jsonb_schema-0.7.0.dist-info/LICENSE
django_jsonb_schema-0.7.0.dist-info/METADATA
django_jsonb_schema-0.7.0.dist-info/WHEEL
django_jsonb_schema-0.7.0.dist-info/top_level.txt
django_jsonb_schema-0.7.0.dist-info/RECORD
